myrich_mohammed/__init__.py
myrich_mohammed-0.1.0.dist-info/licenses/LICENSE
myrich_mohammed-0.1.0.dist-info/WHEEL
myrich_mohammed-0.1.0.dist-info/METADATA
myrich_mohammed-0.1.0.dist-info/RECORD
