Metadata-Version: 2.4
Name: myrich_mohammed
Version: 0.1.0
Summary: Simple library for rich-based input and color preview
Author-email: Mohammed <mohammed023322@gmail.com>
Requires-Python: >=3.7
License-File: LICENSE
Requires-Dist: rich
